README.md
setup.py
taglightswitch/__init__.py
taglightswitch/check_lightswitches
taglightswitch/controltags.py
taglightswitch/lightswitch.py
taglightswitch/switchableitem.py
taglightswitch.egg-info/PKG-INFO
taglightswitch.egg-info/SOURCES.txt
taglightswitch.egg-info/dependency_links.txt
taglightswitch.egg-info/not-zip-safe
taglightswitch.egg-info/requires.txt
taglightswitch.egg-info/top_level.txt