Metadata-Version: 1.0
Name: taglightswitch
Version: 0.1.2
Summary: schedule EC2 instances on/off based on tags
Home-page: http://github.com/bbacker/taglightswitch
Author: Bryan Backer
Author-email: bryan.backer@gmail.com
License: MIT
Platform: UNKNOWN
